README.txt
setup.py
docs/HISTORY.txt
docs/TODO.txt
src/collective/__init__.py
src/collective.contemplate.egg-info/PKG-INFO
src/collective.contemplate.egg-info/SOURCES.txt
src/collective.contemplate.egg-info/dependency_links.txt
src/collective.contemplate.egg-info/entry_points.txt
src/collective.contemplate.egg-info/namespace_packages.txt
src/collective.contemplate.egg-info/not-zip-safe
src/collective.contemplate.egg-info/requires.txt
src/collective.contemplate.egg-info/top_level.txt
src/collective/contemplate/README.txt
src/collective/contemplate/__init__.py
src/collective/contemplate/at.pt
src/collective/contemplate/at.py
src/collective/contemplate/atct.zcml
src/collective/contemplate/base.zcml
src/collective/contemplate/compatible.txt
src/collective/contemplate/configure.zcml
src/collective/contemplate/dynamic.py
src/collective/contemplate/form.py
src/collective/contemplate/interfaces.py
src/collective/contemplate/login.py
src/collective/contemplate/macros.pt
src/collective/contemplate/meta.py
src/collective/contemplate/meta.zcml
src/collective/contemplate/owner.py
src/collective/contemplate/testing.py
src/collective/contemplate/tests.py
src/collective/contemplate/typeinfo.py
src/collective/contemplate/profiles/clear/types.xml
src/collective/contemplate/profiles/default/metadata.xml
src/collective/contemplate/profiles/default/types.xml
src/collective/contemplate/profiles/default/types/Document.xml
src/collective/contemplate/profiles/default/types/Event.xml
src/collective/contemplate/profiles/default/types/Favorite.xml
src/collective/contemplate/profiles/default/types/File.xml
src/collective/contemplate/profiles/default/types/Folder.xml
src/collective/contemplate/profiles/default/types/Image.xml
src/collective/contemplate/profiles/default/types/Large_Plone_Folder.xml
src/collective/contemplate/profiles/default/types/Link.xml
src/collective/contemplate/profiles/default/types/News_Item.xml
src/collective/contemplate/profiles/default/types/Topic.xml