Metadata-Version: 1.0
Name: collective.contemplate
Version: 0.1
Summary: Add content from existing content templates
Home-page: http://pypi.python.org/pypi/collective.contemplate
Author: Ross Patterson
Author-email: me@rpatterson.net
License: GPL
Platform: UNKNOWN
Classifier: Programming Language :: Python
Classifier: Topic :: Software Development :: Libraries :: Python Modules
